aprspy/__init__.py
aprspy/components.py
aprspy/exceptions.py
aprspy/packets/__init__.py
aprspy/packets/beacon.py
aprspy/packets/generic.py
aprspy/packets/message.py
aprspy/packets/mice.py
aprspy/packets/object.py
aprspy/packets/position.py
aprspy/packets/station_capability.py
aprspy/packets/status.py
aprspy/packets/telemetry.py
aprspy/packets/telemetry_definition.py
aprspy/utils.py
aprspy-0.4.0.dist-info/COPYING
aprspy-0.4.0.dist-info/LICENSE
aprspy-0.4.0.dist-info/METADATA
aprspy-0.4.0.dist-info/WHEEL
aprspy-0.4.0.dist-info/RECORD
