Metadata-Version: 2.3
Name: aprspy
Version: 0.4.0
Summary: APRS packet parser for Python
License: MIT
Author: Andy Smith
Author-email: andy@nsnw.ca
Requires-Python: >=3.10,<4.0
Classifier: License :: OSI Approved :: MIT License
Classifier: Programming Language :: Python :: 3
Classifier: Programming Language :: Python :: 3.10
Classifier: Programming Language :: Python :: 3.11
Classifier: Programming Language :: Python :: 3.12
Classifier: Programming Language :: Python :: 3.13
Requires-Dist: bitstring (>=4.3.0,<5.0.0)
Requires-Dist: geopy (>=2.4.1,<3.0.0)
